talkops/__init__.py
talkops/main.py
talkops_client-0.1.0.dist-info/licenses/LICENSE
talkops_client-0.1.0.dist-info/METADATA
talkops_client-0.1.0.dist-info/WHEEL
talkops_client-0.1.0.dist-info/entry_points.txt
talkops_client-0.1.0.dist-info/top_level.txt
talkops_client-0.1.0.dist-info/RECORD
