Metadata-Version: 2.4
Name: talkops-client
Version: 0.1.0
Summary: TalkOps Client which connects to various TalkOps A2A Servers
License: Apache-2.0
Project-URL: Homepage, https://github.com/yourusername/talkops
Project-URL: Repository, https://github.com/yourusername/talkops
Project-URL: Issues, https://github.com/yourusername/talkops/issues
Keywords: a2a,talkops,agent,client,cli
Classifier: Development Status :: 4 - Beta
Classifier: Intended Audience :: Developers
Classifier: Programming Language :: Python :: 3
Classifier: Programming Language :: Python :: 3.12
Classifier: Programming Language :: Python :: 3.13
Requires-Python: >=3.12
License-File: LICENSE
Requires-Dist: a2a-sdk>=0.3.20
Requires-Dist: asyncclick>=8.3.0.7
Requires-Dist: colorama>=0.4.6
Requires-Dist: httpx>=0.28.0
Dynamic: license-file
